README
pbkdf2.py
setup.py
simple_pbkdf2.egg-info/PKG-INFO
simple_pbkdf2.egg-info/SOURCES.txt
simple_pbkdf2.egg-info/dependency_links.txt
simple_pbkdf2.egg-info/not-zip-safe
simple_pbkdf2.egg-info/top_level.txt