Metadata-Version: 1.1
Name: simple-pbkdf2
Version: 1.0
Summary: A simple and straightforward implementation of pbkdf2.  Also copy/pasteable
Home-page: http://github.com/mitsuhiko/python-pbkdf2
Author: Armin Ronacher
Author-email: armin.ronacher@active-4.com
License: UNKNOWN
Platform: UNKNOWN
Classifier: License :: OSI Approved :: BSD License
Classifier: Programming Language :: Python
